Metadata-Version: 2.1
Name: haar-pytorch
Version: 2021.11.16.0
Summary: Pytorch implementation of the forward and inverse discrete wavelet transform using Haar Wavelets.
Home-page: https://github.com/bes-dev/haar_pytorch
Author: Sergei Belousov aka BeS
Author-email: sergei.o.belousov@gmail.com
License: Apache 2.0
Platform: UNKNOWN
Classifier: Programming Language :: Python :: 3
License-File: LICENSE
